odoo8_addon_medical_medicament-8.0.1.0.0.99.dev10-py2.7-nspkg.pth
odoo8_addon_medical_medicament-8.0.1.0.0.99.dev10.dist-info/DESCRIPTION.rst
odoo8_addon_medical_medicament-8.0.1.0.0.99.dev10.dist-info/METADATA
odoo8_addon_medical_medicament-8.0.1.0.0.99.dev10.dist-info/RECORD
odoo8_addon_medical_medicament-8.0.1.0.0.99.dev10.dist-info/WHEEL
odoo8_addon_medical_medicament-8.0.1.0.0.99.dev10.dist-info/metadata.json
odoo8_addon_medical_medicament-8.0.1.0.0.99.dev10.dist-info/namespace_packages.txt
odoo8_addon_medical_medicament-8.0.1.0.0.99.dev10.dist-info/top_level.txt
odoo_addons/medical_medicament/README.rst
odoo_addons/medical_medicament/__init__.py
odoo_addons/medical_medicament/__openerp__.py
odoo_addons/medical_medicament/data/medical_drug_form.xml
odoo_addons/medical_medicament/data/medical_drug_route.xml
odoo_addons/medical_medicament/i18n/pt_BR.po
odoo_addons/medical_medicament/i18n/sl.po
odoo_addons/medical_medicament/models/__init__.py
odoo_addons/medical_medicament/models/medical_drug_form.py
odoo_addons/medical_medicament/models/medical_drug_route.py
odoo_addons/medical_medicament/models/medical_medicament.py
odoo_addons/medical_medicament/models/product.py
odoo_addons/medical_medicament/security/ir.model.access.csv
odoo_addons/medical_medicament/tests/__init__.py
odoo_addons/medical_medicament/tests/test_medical_medicament.py
odoo_addons/medical_medicament/views/medical_drug_form_view.xml
odoo_addons/medical_medicament/views/medical_drug_route_view.xml
odoo_addons/medical_medicament/views/medical_medicament_view.xml
odoo_addons/medical_medicament/views/product_product_view.xml
